{
  "id": "1d8ef72a-7b54-4230-846d-4fe1a4af63e1",
  "m1_id": 9030,
  "added_at": "2026-02-19T05:19:28.435692Z",
  "play_count": 208,
  "last_played_at": "2025-12-27T17:30:18Z",
  "title": "Asleep In The Hay",
  "artist": "Jonny Diaz",
  "m1_artist_id": 1545,
  "artist2_id": null,
  "alt_artists": "",
  "category": "40037",
  "duration_ms": 225000,
  "duration_seconds": 225,
  "intro_ms": 20000,
  "outro_ms": 0,
  "hook_in_ms": 0,
  "hook_out_ms": 0,
  "mix_in_ms": 0,
  "mix_out_ms": 0,
  "gender": 1,
  "tempo": 3,
  "tempo_min": 3,
  "tempo_max": 3,
  "texture": 0,
  "texture_min": 0,
  "texture_max": 0,
  "mood": 0,
  "key1": 0,
  "key2": 0,
  "bpm": null,
  "sound_codes": [
    7
  ],
  "hour_restricted": false,
  "allowed_hours": "111111111111111111111111",
  "start_hour": 0,
  "end_hour": 23,
  "start_date": "0",
  "end_date": "0",
  "hit_date": "41548",
  "can_open_hour": true,
  "can_close_hour": true,
  "cart": "X656",
  "file_path": "CENTRICITY/ CHR-13",
  "auto_params": "",
  "id_in_player": "",
  "album": "0",
  "genre": "",
  "composer": "Jonny Diaz",
  "arranger": "",
  "publisher": "",
  "record_label": "Centricity",
  "catalog_num": "",
  "origin": "67",
  "prog_type": "78",
  "prod_source": "65",
  "music_usage": "70",
  "isrc_code": "",
  "work_code": "",
  "recording_code": "",
  "native_content": false,
  "mcps": true,
  "prior_approval": false,
  "user1": "Joy To The World",
  "user2": "",
  "user3": "Many a man has sought to be God destroying the world on his way but only 1",
  "user4": "God ever thought to be man and He was born on Christmas day.....",
  "announcer": 0,
  "link_type": 0,
  "link_align": 0,
  "pct_play": 100,
  "chart_position": 0,
  "plays_this_list": 86,
  "date_added": "2013-10-27T00:00:00Z",
  "rotation_ranks": {
    "40037": {
      "rank": 84,
      "play_num": 36,
      "play_credits": 181440
    }
  }
}