{
  "id": "4c240b1f-df0b-41f7-b0a0-414ec19f95f3",
  "m1_id": 7955,
  "added_at": "2026-02-19T05:19:27.996740Z",
  "play_count": 1114,
  "last_played_at": "2024-07-16T19:39:35Z",
  "title": "Everything Glorious",
  "artist": "David Crowder",
  "m1_artist_id": 1291,
  "artist2_id": null,
  "alt_artists": "",
  "category": "40001",
  "duration_ms": 256000,
  "duration_seconds": 256,
  "intro_ms": 11000,
  "outro_ms": 0,
  "hook_in_ms": 0,
  "hook_out_ms": 0,
  "mix_in_ms": 0,
  "mix_out_ms": 0,
  "gender": 3,
  "tempo": 5,
  "tempo_min": 5,
  "tempo_max": 5,
  "texture": 0,
  "texture_min": 0,
  "texture_max": 0,
  "mood": 0,
  "key1": 0,
  "key2": 0,
  "bpm": null,
  "sound_codes": [
    6
  ],
  "hour_restricted": false,
  "allowed_hours": "111111111111111111111111",
  "start_hour": 0,
  "end_hour": 23,
  "start_date": "0",
  "end_date": "0",
  "hit_date": "38838",
  "can_open_hour": true,
  "can_close_hour": true,
  "cart": "T959",
  "file_path": "PASSION-06",
  "auto_params": "",
  "id_in_player": "",
  "album": "0",
  "genre": "",
  "composer": "",
  "arranger": "",
  "publisher": "",
  "record_label": "Sparrow",
  "catalog_num": "",
  "origin": "67",
  "prog_type": "78",
  "prod_source": "65",
  "music_usage": "70",
  "isrc_code": "",
  "work_code": "",
  "recording_code": "",
  "native_content": false,
  "mcps": true,
  "prior_approval": false,
  "user1": "Everything Glorious",
  "user2": "",
  "user3": "The day is brighter here with You the night is lighter than it's hue",
  "user4": "which leads me to believe You make everything glorious....",
  "announcer": 0,
  "link_type": 0,
  "link_align": 0,
  "pct_play": 100,
  "chart_position": 0,
  "plays_this_list": 0,
  "date_added": "2006-05-03T00:00:00Z",
  "rotation_ranks": {
    "40001": {
      "rank": 1481,
      "play_num": 0,
      "play_credits": 0
    }
  }
}