{
  "id": "6b5f0a61-c9a0-4003-a502-02b5386888f7",
  "m1_id": 8989,
  "added_at": "2026-02-19T05:19:28.418595Z",
  "play_count": 792,
  "last_played_at": "2026-03-01T16:55:03Z",
  "title": "I Will Exalt You",
  "artist": "Hillsong Live",
  "m1_artist_id": 1560,
  "artist2_id": null,
  "alt_artists": "",
  "category": "40007",
  "duration_ms": 291000,
  "duration_seconds": 291,
  "intro_ms": 4000,
  "outro_ms": 0,
  "hook_in_ms": 0,
  "hook_out_ms": 0,
  "mix_in_ms": 0,
  "mix_out_ms": 0,
  "gender": 0,
  "tempo": 1,
  "tempo_min": 1,
  "tempo_max": 1,
  "texture": 0,
  "texture_min": 0,
  "texture_max": 0,
  "mood": 0,
  "key1": 0,
  "key2": 0,
  "bpm": null,
  "sound_codes": [
    5
  ],
  "hour_restricted": false,
  "allowed_hours": "111111111111111111111111",
  "start_hour": 0,
  "end_hour": 23,
  "start_date": "0",
  "end_date": "0",
  "hit_date": "0",
  "can_open_hour": true,
  "can_close_hour": true,
  "cart": "V623",
  "file_path": "HILLSONGLIVE-10",
  "auto_params": "",
  "id_in_player": "",
  "album": "0",
  "genre": "",
  "composer": "Brooke Ligertwood",
  "arranger": "",
  "publisher": "",
  "record_label": "Hillsong",
  "catalog_num": "",
  "origin": "67",
  "prog_type": "78",
  "prod_source": "65",
  "music_usage": "70",
  "isrc_code": "",
  "work_code": "",
  "recording_code": "",
  "native_content": false,
  "mcps": true,
  "prior_approval": false,
  "user1": "Faith + Hope + Love",
  "user2": "",
  "user3": "I will exalt you......You are my God My hiding place my safe refuge my treasure",
  "user4": "Lord You are my friend and King Anointed One most holy...........",
  "announcer": 0,
  "link_type": 0,
  "link_align": 0,
  "pct_play": 100,
  "chart_position": 0,
  "plays_this_list": 91,
  "date_added": "2013-05-07T00:00:00Z",
  "rotation_ranks": {
    "40007": {
      "rank": 23,
      "play_num": 4,
      "play_credits": 20160
    }
  }
}