{
  "id": "ed3d5e74-84fe-4e1e-9326-c0f3af5b3b33",
  "m1_id": 8722,
  "added_at": "2026-02-19T05:19:28.104758Z",
  "play_count": 277,
  "last_played_at": "2025-12-03T19:51:21Z",
  "title": "Come Now Our King",
  "artist": "Chris August",
  "m1_artist_id": 1569,
  "artist2_id": null,
  "alt_artists": "",
  "category": "40001",
  "duration_ms": 220000,
  "duration_seconds": 220,
  "intro_ms": 8000,
  "outro_ms": 0,
  "hook_in_ms": 0,
  "hook_out_ms": 0,
  "mix_in_ms": 0,
  "mix_out_ms": 220000,
  "gender": 1,
  "tempo": 5,
  "tempo_min": 5,
  "tempo_max": 5,
  "texture": 0,
  "texture_min": 0,
  "texture_max": 0,
  "mood": 0,
  "key1": 0,
  "key2": 0,
  "bpm": null,
  "sound_codes": [
    7
  ],
  "hour_restricted": false,
  "allowed_hours": "111111111111111111111111",
  "start_hour": 0,
  "end_hour": 23,
  "start_date": "0",
  "end_date": "0",
  "hit_date": "40483",
  "can_open_hour": true,
  "can_close_hour": true,
  "cart": "X606",
  "file_path": "WORDCHR/VAR-10",
  "auto_params": "",
  "id_in_player": "",
  "album": "0",
  "genre": "",
  "composer": "",
  "arranger": "",
  "publisher": "",
  "record_label": "Word",
  "catalog_num": "",
  "origin": "67",
  "prog_type": "78",
  "prod_source": "65",
  "music_usage": "70",
  "isrc_code": "",
  "work_code": "",
  "recording_code": "",
  "native_content": false,
  "mcps": true,
  "prior_approval": false,
  "user1": "Happy Christmas    Word Christmas Sampler",
  "user2": "",
  "user3": "Bethlehem turns into night a town lit up by candle light all the children tucked",
  "user4": "in tight bethlehem turns into nght angels start their whispering....",
  "announcer": 0,
  "link_type": 0,
  "link_align": 0,
  "pct_play": 100,
  "chart_position": 0,
  "plays_this_list": 0,
  "date_added": "2010-10-24T00:00:00Z",
  "rotation_ranks": {
    "40001": {
      "rank": 1642,
      "play_num": 0,
      "play_credits": 0
    }
  }
}